Metadata-Version: 2.1
Name: color-terminal
Version: 1.0
Summary: Color terminal
Home-page: UNKNOWN
Author-email: easyhelloworld228@gmail.com
License: UNKNOWN
Platform: UNKNOWN
